tmalibrary/__init__.py
tmalibrary/actuator/ActuatorPayload.py
tmalibrary/actuator/HandleRequest.py
tmalibrary/actuator/KeyManager.py
tmalibrary/actuator/__init__.py
tmalibrary/probes/__init__.py
tmalibrary/probes/communication.py
tmalibrary/probes/data.py
tmalibrary/probes/message.py
tmalibrary/probes/observation.py
tmalibrary-10.0.dist-info/LICENSE.txt
tmalibrary-10.0.dist-info/METADATA
tmalibrary-10.0.dist-info/WHEEL
tmalibrary-10.0.dist-info/top_level.txt
tmalibrary-10.0.dist-info/RECORD
