Metadata-Version: 2.1
Name: tmalibrary
Version: 10.0
Summary: Probe and Actuator Library
Home-page: https://github.com/rfrsilva/tmalibrary
Author: Rui Silva
Author-email: rfsilva@student.dei.uc.pt
License: UNKNOWN
Platform: UNKNOWN
Classifier: Programming Language :: Python :: 3
Classifier: License :: OSI Approved :: MIT License
Classifier: Operating System :: OS Independent
